ceepur_scraper/__init__.py
ceepur_scraper/csv_writer.py
ceepur_scraper/models.py
ceepur_scraper-0.1.1.dist-info/METADATA
ceepur_scraper-0.1.1.dist-info/WHEEL
ceepur_scraper-0.1.1.dist-info/entry_points.txt
ceepur_scraper-0.1.1.dist-info/RECORD
