Metadata-Version: 2.1
Name: ceepur-scraper
Version: 0.1.1
Summary: Un programa para extraer todos los datos públicos del registro electoral de Puerto Rico, accesibles a través de https://consulta.ceepur.org/
Home-page: https://github.com/jicruz96/ceepur-scraper
Keywords: puerto-rico,electoral,scraper,ceepur
Author: J.I. Cruz
Author-email: ji@jicruz.com
Requires-Python: >=3.9,<4.0
Classifier: Programming Language :: Python :: 3
Classifier: Programming Language :: Python :: 3.9
Classifier: Programming Language :: Python :: 3.10
Classifier: Programming Language :: Python :: 3.11
Classifier: Programming Language :: Python :: 3.12
Requires-Dist: aiohttp (>=3.10.7,<4.0.0)
Requires-Dist: random-user-agent (>=1.0.1,<2.0.0)
Requires-Dist: tqdm (>=4.66.5,<5.0.0)
Requires-Dist: xmltodict (>=0.13.0,<0.14.0)
Project-URL: Repository, https://github.com/jicruz96/ceepur-scraper
